{
  "title": "The Paris Diversion (Kate Moore, #2)",
  "author": "Chris  Pavone",
  "dateFinished": "2022-10-20",
  "genre": "Unknown",
  "pages": 379,
  "readingYear": 2022,
  "readingMonth": 10,
  "isCurrentlyReading": false,
  "goodreadsId": "41145585",
  "rating": 0,
  "enhancedGenre": "Thriller, Mystery",
  "bookCategory": "Fiction",
  "readingLevel": "Intermediate",
  "themes": [
    "Espionage",
    "Betrayal",
    "Survival",
    "International Intrigue"
  ],
  "targetAudience": "Readers who enjoy suspenseful thrillers and mysteries",
  "complexity": "Moderate",
  "readingTime": "8 hours",
  "relatedBooks": [
    "The Expats",
    "The Other Woman",
    "The Spy Who Came in from the Cold"
  ],
  "keyInsights": [
    "Exploration of trust and deception",
    "The impact of past decisions on present circumstances",
    "The complexity of human relationships in high-stakes environments"
  ],
  "tags": [
    "Thriller",
    "Mystery",
    "Espionage",
    "Suspense",
    "Fiction"
  ],
  "llmProcessed": true,
  "llmProcessedAt": "2026-03-06T13:26:45.205Z",
  "localCoverPath": "/book-covers/the-paris-diversion-kate-moore-2-chris-pavone.jpg",
  "coverUrl": "https://covers.openlibrary.org/b/id/8798597-M.jpg"
}